ndx_photostim/__init__.py
ndx_photostim/photostim.py
ndx_photostim/spec/ndx-photostim.extensions.yaml
ndx_photostim/spec/ndx-photostim.namespace.yaml
ndx_photostim-0.0.4.dist-info/LICENSE
ndx_photostim-0.0.4.dist-info/METADATA
ndx_photostim-0.0.4.dist-info/WHEEL
ndx_photostim-0.0.4.dist-info/top_level.txt
ndx_photostim-0.0.4.dist-info/RECORD
