Metadata-Version: 2.1
Name: ndx-photostim
Version: 0.0.4
Summary: Holographic photostimulation extension to NWB standard
Home-page: 
Author: Paul LaFosse, Carl Harris
Author-email: Paul LaFosse <paul.lafosse@nih.gov>, Carl Harris <carl.harris@nih.gov>, Adam Thomas <adam.thomas@nih.gov>, Mark Histed <mark.histed@nih.gov>
License: MIT
Project-URL: Homepage, https://github.com/histedlab/ndx-photostim
Project-URL: Bug Tracker, https://github.com/histedlab/ndx-photostim/issues
Keywords: NeurodataWithoutBorders,NWB,nwb-extension,ndx-extension
Classifier: Programming Language :: Python :: 3
Classifier: License :: OSI Approved :: MIT License
Classifier: Operating System :: OS Independent
Requires-Python: >=3.7
License-File: LICENSE
Requires-Dist: pynwb <3,>=1.5.0
Requires-Dist: hdmf <4,>=2.5.6
